<?xml version="1.0" encoding="UTF-8"?>
<rdf:RDF xmlns="http://purl.org/rss/1.0/"
         xmlns:rdf="http://www.w3.org/1999/02/22-rdf-syntax-ns#"
         xmlns:dc="http://purl.org/dc/elements/1.1/">
  <channel rdf:about="https://assets.wor.jp/rss/rss/rdf/ynnews/politics.rdf"
           encoded="https%3A%2F%2Fassets.wor.jp%2Frss%2Frss%2Frdf%2Fynnews%2Fpolitics.rdf">
    <title>47NEWS 全国 政治</title>
    <link>https://www.47news.jp/news/politics</link>
    <description>47NEWS 全国の政治に関するフィードをお届けします。</description>
    <dc:date>2026-02-04T19:12:45+09:00</dc:date>
    <dc:language>ja</dc:language>
    <items>
      <rdf:Seq>
        <rdf:li rdf:resource="https://www.47news.jp/13819326.html"/>
        <rdf:li rdf:resource="https://www.47news.jp/13818248.html"/>
        <rdf:li rdf:resource="https://www.47news.jp/13819203.html"/>
        <rdf:li rdf:resource="https://www.47news.jp/13819227.html"/>
        <rdf:li rdf:resource="https://www.47news.jp/13819318.html"/>
        <rdf:li rdf:resource="https://www.47news.jp/13819131.html"/>
        <rdf:li rdf:resource="https://www.47news.jp/13819158.html"/>
        <rdf:li rdf:resource="https://www.47news.jp/13819005.html"/>
        <rdf:li rdf:resource="https://www.47news.jp/13819007.html"/>
        <rdf:li rdf:resource="https://www.47news.jp/13819333.html"/>
        <rdf:li rdf:resource="https://www.47news.jp/13819038.html"/>
        <rdf:li rdf:resource="https://www.47news.jp/13819025.html"/>
        <rdf:li rdf:resource="https://www.47news.jp/13818933.html"/>
        <rdf:li rdf:resource="https://www.47news.jp/13818887.html"/>
        <rdf:li rdf:resource="https://www.47news.jp/13818952.html"/>
        <rdf:li rdf:resource="https://www.47news.jp/13818805.html"/>
        <rdf:li rdf:resource="https://www.47news.jp/13818897.html"/>
        <rdf:li rdf:resource="https://www.47news.jp/13818795.html"/>
        <rdf:li rdf:resource="https://www.47news.jp/13818498.html"/>
        <rdf:li rdf:resource="https://www.47news.jp/13818741.html"/>
        <rdf:li rdf:resource="https://www.47news.jp/12793427.html"/>
        <rdf:li rdf:resource="https://www.47news.jp/13814285.html"/>
        <rdf:li rdf:resource="https://www.47news.jp/13817830.html"/>
        <rdf:li rdf:resource="https://www.47news.jp/13802054.html"/>
        <rdf:li rdf:resource="https://www.47news.jp/13814222.html"/>
        <rdf:li rdf:resource="https://www.47news.jp/special/goto_retto_christian_monogatari_01"/>
        <rdf:li rdf:resource="https://www.47news.jp/special/university-future"/>
        <rdf:li rdf:resource="https://www.47news.jp/special/e-fran_06"/>
        <rdf:li rdf:resource="https://www.47news.jp/special/e-fran_05"/>
        <rdf:li rdf:resource="https://www.47news.jp/special/kenes_03"/>
        <rdf:li rdf:resource="https://www.47news.jp/special/goto_retto_christian_monogatari_top"/>
        <rdf:li rdf:resource="https://www.47news.jp/special/goto_retto_christian_monogatari_01"/>
        <rdf:li rdf:resource="https://www.47news.jp/special/university-future"/>
      </rdf:Seq>
    </items>
  </channel>
  <item rdf:about="https://www.47news.jp/13819326.html">
    <title>＜衆院選　私の一票＞物価高や少子高齢化対策を　精肉店経営・梶田学さん（49）＝浦河町</title>
    <link>https://www.47news.jp/13819326.html</link>
    <description></description>
    <dc:date>2026-02-04T00:00:00+09:00</dc:date>
  </item>
  <item rdf:about="https://www.47news.jp/13818248.html">
    <title>希少資源の調達、各党が訴え　中国輸出規制に危機感</title>
    <link>https://www.47news.jp/13818248.html</link>
    <description></description>
    <dc:date>2026-02-04T00:00:00+09:00</dc:date>
  </item>
  <item rdf:about="https://www.47news.jp/13819203.html">
    <title>首相、経済成長へ投資促進　野田氏、食品消費税ゼロを</title>
    <link>https://www.47news.jp/13819203.html</link>
    <description></description>
    <dc:date>2026-02-04T00:00:00+09:00</dc:date>
  </item>
  <item rdf:about="https://www.47news.jp/13819227.html">
    <title>【速報】総務省、みらいの比例近畿候補1人を抹消</title>
    <link>https://www.47news.jp/13819227.html</link>
    <description></description>
    <dc:date>2026-02-04T00:00:00+09:00</dc:date>
  </item>
  <item rdf:about="https://www.47news.jp/13819318.html">
    <title>＜衆院選道6区　現場から＞㊤物価高　暮らし切実、減税に効果は</title>
    <link>https://www.47news.jp/13819318.html</link>
    <description></description>
    <dc:date>2026-02-04T00:00:00+09:00</dc:date>
  </item>
  <item rdf:about="https://www.47news.jp/13819131.html">
    <title>防衛省、太平洋諸国と協力強化　小泉氏が下旬に国際会合</title>
    <link>https://www.47news.jp/13819131.html</link>
    <description></description>
    <dc:date>2026-02-04T00:00:00+09:00</dc:date>
  </item>
  <item rdf:about="https://www.47news.jp/13819158.html">
    <title>非核三原則の岐路、衆院選の論戦見守る被爆者「議論尽くして」</title>
    <link>https://www.47news.jp/13819158.html</link>
    <description></description>
    <dc:date>2026-02-04T00:00:00+09:00</dc:date>
  </item>
  <item rdf:about="https://www.47news.jp/13819005.html">
    <title>大雪死者、8道県で35人　総務省消防庁まとめ</title>
    <link>https://www.47news.jp/13819005.html</link>
    <description></description>
    <dc:date>2026-02-04T00:00:00+09:00</dc:date>
  </item>
  <item rdf:about="https://www.47news.jp/13819007.html">
    <title>衆院選、X投稿は「消費税」最多　外国人政策、旧統一教会続く</title>
    <link>https://www.47news.jp/13819007.html</link>
    <description></description>
    <dc:date>2026-02-04T00:00:00+09:00</dc:date>
  </item>
  <item rdf:about="https://www.47news.jp/13819333.html">
    <title>日本の食どう守る?　コメ生産者の減少、兵庫県内でも急速に進む　問われる持続的な発展や安定供給</title>
    <link>https://www.47news.jp/13819333.html</link>
    <description></description>
    <dc:date>2026-02-04T00:00:00+09:00</dc:date>
  </item>
  <item rdf:about="https://www.47news.jp/13819038.html">
    <title>福山で衆院選投票を買い物客に呼びかけ</title>
    <link>https://www.47news.jp/13819038.html</link>
    <description></description>
    <dc:date>2026-02-04T00:00:00+09:00</dc:date>
  </item>
  <item rdf:about="https://www.47news.jp/13819025.html">
    <title>南あわじ市の期日前投票　2カ所で国民審査の投票用紙の交付ミス　渡し損ねた可能性</title>
    <link>https://www.47news.jp/13819025.html</link>
    <description></description>
    <dc:date>2026-02-04T00:00:00+09:00</dc:date>
  </item>
  <item rdf:about="https://www.47news.jp/13818933.html">
    <title>チームみらい、比例1人取り消し　近畿、粉飾企業に雇用歴</title>
    <link>https://www.47news.jp/13818933.html</link>
    <description></description>
    <dc:date>2026-02-04T00:00:00+09:00</dc:date>
  </item>
  <item rdf:about="https://www.47news.jp/13818887.html">
    <title>【衆議院選挙2026】村上市の官民関係者ら日東道延伸に期待　観光面の効果や救急搬送時間短縮の利点訴え　「地域は訴える」</title>
    <link>https://www.47news.jp/13818887.html</link>
    <description></description>
    <dc:date>2026-02-04T00:00:00+09:00</dc:date>
  </item>
  <item rdf:about="https://www.47news.jp/13818952.html">
    <title>秋田県内の投票所、前回衆院選から１９カ所減る　期日前普及や人手不足で</title>
    <link>https://www.47news.jp/13818952.html</link>
    <description></description>
    <dc:date>2026-02-04T00:00:00+09:00</dc:date>
  </item>
  <item rdf:about="https://www.47news.jp/13818805.html">
    <title>【速報】みらい、衆院選比例近畿の公認1人取り消し</title>
    <link>https://www.47news.jp/13818805.html</link>
    <description></description>
    <dc:date>2026-02-04T00:00:00+09:00</dc:date>
  </item>
  <item rdf:about="https://www.47news.jp/13818897.html">
    <title>衆院選投票用紙を二重に交付　柳井市選管　1人が投票</title>
    <link>https://www.47news.jp/13818897.html</link>
    <description></description>
    <dc:date>2026-02-04T00:00:00+09:00</dc:date>
  </item>
  <item rdf:about="https://www.47news.jp/13818795.html">
    <title>高市首相が熱望する衆院の「委員長ポスト」って?　政党の国会戦略と連動＜かほQチェック＞</title>
    <link>https://www.47news.jp/13818795.html</link>
    <description></description>
    <dc:date>2026-02-04T00:00:00+09:00</dc:date>
  </item>
  <item rdf:about="https://www.47news.jp/13818498.html">
    <title>外国人、国民健康保険支える面も　百田代表は「ただ乗り」と発言</title>
    <link>https://www.47news.jp/13818498.html</link>
    <description></description>
    <dc:date>2026-02-04T00:00:00+09:00</dc:date>
  </item>
  <item rdf:about="https://www.47news.jp/13818741.html">
    <title>【衆院選２０２６】苦戦の中道、狭まる比例復活枠巡り「身内の競り合い」　神奈川や千葉の陣営、気をもむ惜敗率</title>
    <link>https://www.47news.jp/13818741.html</link>
    <description></description>
    <dc:date>2026-02-04T00:00:00+09:00</dc:date>
  </item>
  <item rdf:about="https://www.47news.jp/12793427.html">
    <title>知事給与平均1954万円　24年報告書、増額30人</title>
    <link>https://www.47news.jp/12793427.html</link>
    <description></description>
    <dc:date>2026-02-04T00:00:00+09:00</dc:date>
  </item>
  <item rdf:about="https://www.47news.jp/13814285.html">
    <title>衆院選比例　島根は自民、鳥取は中道トップ　本社世論調査詳報　〈衆院選2026〉</title>
    <link>https://www.47news.jp/13814285.html</link>
    <description></description>
    <dc:date>2026-02-04T00:00:00+09:00</dc:date>
  </item>
  <item rdf:about="https://www.47news.jp/13817830.html">
    <title>神奈川の黒岩知事が入院　慢性硬膜下血腫、会話可能</title>
    <link>https://www.47news.jp/13817830.html</link>
    <description></description>
    <dc:date>2026-02-04T00:00:00+09:00</dc:date>
  </item>
  <item rdf:about="https://www.47news.jp/13802054.html">
    <title>米価格高止まり、だぶつく在庫　増産方針撤回に候補者は【ふるさと番外編】①</title>
    <link>https://www.47news.jp/13802054.html</link>
    <description></description>
    <dc:date>2026-02-04T00:00:00+09:00</dc:date>
  </item>
  <item rdf:about="https://www.47news.jp/13814222.html">
    <title>中道、政権批判で反転攻勢　自民、優勢維持へ票固め</title>
    <link>https://www.47news.jp/13814222.html</link>
    <description></description>
    <dc:date>2026-02-04T00:00:00+09:00</dc:date>
  </item>
  <item rdf:about="https://www.47news.jp/special/goto_retto_christian_monogatari_01">
    <title>五島列島キリシタン物語【前編】　地元新聞社が発行している生活情報誌ライターの旅日記をお届け。</title>
    <link>https://www.47news.jp/special/goto_retto_christian_monogatari_01</link>
    <description></description>
    <dc:date>2026-02-04T00:00:00+09:00</dc:date>
  </item>
  <item rdf:about="https://www.47news.jp/special/university-future">
    <title>大学特集〜大学教育の未来を探る〜</title>
    <link>https://www.47news.jp/special/university-future</link>
    <description></description>
    <dc:date>2026-02-04T00:00:00+09:00</dc:date>
  </item>
  <item rdf:about="https://www.47news.jp/special/e-fran_06">
    <title>創業5年で売り上げ50億円達成の背景に「自責」の精神　渡辺喜久男会長と塚本拓夢オーナーが「おたからや」の成功を語る</title>
    <link>https://www.47news.jp/special/e-fran_06</link>
    <description></description>
    <dc:date>2026-02-04T00:00:00+09:00</dc:date>
  </item>
  <item rdf:about="https://www.47news.jp/special/e-fran_05">
    <title>「おたからや」に学ぶ、FC経営成功の秘訣　大畑典道オーナーと渡辺喜久男会長が本音で語る</title>
    <link>https://www.47news.jp/special/e-fran_05</link>
    <description></description>
    <dc:date>2026-02-04T00:00:00+09:00</dc:date>
  </item>
  <item rdf:about="https://www.47news.jp/special/kenes_03">
    <title>幅広い知識と技術で、顧客の省エネを支え続ける　最前線で奮闘するKenesの社員たち</title>
    <link>https://www.47news.jp/special/kenes_03</link>
    <description></description>
    <dc:date>2026-02-04T00:00:00+09:00</dc:date>
  </item>
  <item rdf:about="https://www.47news.jp/special/goto_retto_christian_monogatari_top">
    <title>五島列島キリシタン物語　五島市・新上五島町・小値賀町【周遊編】</title>
    <link>https://www.47news.jp/special/goto_retto_christian_monogatari_top</link>
    <description></description>
    <dc:date>2026-02-04T00:00:00+09:00</dc:date>
  </item>
  <item rdf:about="https://www.47news.jp/special/goto_retto_christian_monogatari_01">
    <title>五島列島キリシタン物語【前編】　地元新聞社が発行している生活情報誌ライターの旅日記をお届け。</title>
    <link>https://www.47news.jp/special/goto_retto_christian_monogatari_01</link>
    <description></description>
    <dc:date>2026-02-04T00:00:00+09:00</dc:date>
  </item>
  <item rdf:about="https://www.47news.jp/special/university-future">
    <title>大学特集〜大学教育の未来を探る〜</title>
    <link>https://www.47news.jp/special/university-future</link>
    <description></description>
    <dc:date>2026-02-04T00:00:00+09:00</dc:date>
  </item>
</rdf:RDF>
