<?xml version="1.0" encoding="UTF-8"?>
<rdf:RDF xmlns="http://purl.org/rss/1.0/"
         xmlns:rdf="http://www.w3.org/1999/02/22-rdf-syntax-ns#"
         xmlns:dc="http://purl.org/dc/elements/1.1/">
  <channel rdf:about="https://assets.wor.jp/rss/rss/rdf/ynnews/politics.rdf"
           encoded="https%3A%2F%2Fassets.wor.jp%2Frss%2Frss%2Frdf%2Fynnews%2Fpolitics.rdf">
    <title>47NEWS 全国 政治</title>
    <link>https://www.47news.jp/news/politics</link>
    <description>47NEWS 全国の政治に関するフィードをお届けします。</description>
    <dc:date>2026-07-17T13:12:50+09:00</dc:date>
    <dc:language>ja</dc:language>
    <items>
      <rdf:Seq>
        <rdf:li rdf:resource="https://www.47news.jp/14638291.html"/>
        <rdf:li rdf:resource="https://www.47news.jp/14637969.html"/>
        <rdf:li rdf:resource="https://www.47news.jp/14637968.html"/>
        <rdf:li rdf:resource="https://www.47news.jp/14637961.html"/>
        <rdf:li rdf:resource="https://www.47news.jp/14637967.html"/>
        <rdf:li rdf:resource="https://www.47news.jp/14637715.html"/>
        <rdf:li rdf:resource="https://www.47news.jp/14637525.html"/>
        <rdf:li rdf:resource="https://www.47news.jp/14637595.html"/>
        <rdf:li rdf:resource="https://www.47news.jp/14637360.html"/>
        <rdf:li rdf:resource="https://www.47news.jp/14636911.html"/>
        <rdf:li rdf:resource="https://www.47news.jp/14636322.html"/>
        <rdf:li rdf:resource="https://www.47news.jp/14636252.html"/>
        <rdf:li rdf:resource="https://www.47news.jp/14633802.html"/>
        <rdf:li rdf:resource="https://www.47news.jp/14635356.html"/>
        <rdf:li rdf:resource="https://www.47news.jp/14632912.html"/>
        <rdf:li rdf:resource="https://www.47news.jp/14635076.html"/>
        <rdf:li rdf:resource="https://www.47news.jp/14632261.html"/>
        <rdf:li rdf:resource="https://www.47news.jp/14634966.html"/>
        <rdf:li rdf:resource="https://www.47news.jp/14634846.html"/>
        <rdf:li rdf:resource="https://www.47news.jp/14631002.html"/>
        <rdf:li rdf:resource="https://www.47news.jp/14633802.html"/>
        <rdf:li rdf:resource="https://www.47news.jp/14629683.html"/>
        <rdf:li rdf:resource="https://www.47news.jp/14632912.html"/>
        <rdf:li rdf:resource="https://www.47news.jp/14636322.html"/>
        <rdf:li rdf:resource="https://www.47news.jp/14636252.html"/>
        <rdf:li rdf:resource="https://www.47news.jp/special/kenes_03"/>
        <rdf:li rdf:resource="https://www.47news.jp/special/env_fukushima"/>
        <rdf:li rdf:resource="https://www.47news.jp/special/nayami_sodan"/>
        <rdf:li rdf:resource="https://www.47news.jp/special/university-future"/>
        <rdf:li rdf:resource="https://www.47news.jp/special/e-fran_06"/>
        <rdf:li rdf:resource="https://www.47news.jp/special/e-fran_05"/>
        <rdf:li rdf:resource="https://www.47news.jp/special/kenes_03"/>
        <rdf:li rdf:resource="https://www.47news.jp/special/env_fukushima"/>
      </rdf:Seq>
    </items>
  </channel>
  <item rdf:about="https://www.47news.jp/14638291.html">
    <title>知事選・松山市長選の日程決定　１１月１５日投開票</title>
    <link>https://www.47news.jp/14638291.html</link>
    <description></description>
    <dc:date>2026-07-17T00:00:00+09:00</dc:date>
  </item>
  <item rdf:about="https://www.47news.jp/14637969.html">
    <title>【速報】改正皇室典範が参院本会議で成立</title>
    <link>https://www.47news.jp/14637969.html</link>
    <description></description>
    <dc:date>2026-07-17T00:00:00+09:00</dc:date>
  </item>
  <item rdf:about="https://www.47news.jp/14637968.html">
    <title>【速報】改正皇室典範が成立</title>
    <link>https://www.47news.jp/14637968.html</link>
    <description></description>
    <dc:date>2026-07-17T00:00:00+09:00</dc:date>
  </item>
  <item rdf:about="https://www.47news.jp/14637961.html">
    <title>参院本会議で改正皇室典範成立　養子の男性子孫に皇位継承権</title>
    <link>https://www.47news.jp/14637961.html</link>
    <description></description>
    <dc:date>2026-07-17T00:00:00+09:00</dc:date>
  </item>
  <item rdf:about="https://www.47news.jp/14637967.html">
    <title>【速報】改正皇室典範成立、養子の子孫に皇位継承権</title>
    <link>https://www.47news.jp/14637967.html</link>
    <description></description>
    <dc:date>2026-07-17T00:00:00+09:00</dc:date>
  </item>
  <item rdf:about="https://www.47news.jp/14637715.html">
    <title>日本国旗、損壊で刑罰　法成立、運用に課題</title>
    <link>https://www.47news.jp/14637715.html</link>
    <description></description>
    <dc:date>2026-07-17T00:00:00+09:00</dc:date>
  </item>
  <item rdf:about="https://www.47news.jp/14637525.html">
    <title>地域未来戦略着実推進を　国への提言集約人材の確保・育成強調　全国知事会人口減対応チーム新設</title>
    <link>https://www.47news.jp/14637525.html</link>
    <description></description>
    <dc:date>2026-07-17T00:00:00+09:00</dc:date>
  </item>
  <item rdf:about="https://www.47news.jp/14637595.html">
    <title>「第三の居場所」とは　南相馬　ＮＰＯなどが説明会</title>
    <link>https://www.47news.jp/14637595.html</link>
    <description></description>
    <dc:date>2026-07-17T00:00:00+09:00</dc:date>
  </item>
  <item rdf:about="https://www.47news.jp/14637360.html">
    <title>【速報】国旗損壊罪法が成立</title>
    <link>https://www.47news.jp/14637360.html</link>
    <description></description>
    <dc:date>2026-07-17T00:00:00+09:00</dc:date>
  </item>
  <item rdf:about="https://www.47news.jp/14636911.html">
    <title>人口減対応チーム新設　客観データで分析・検証　全国知事会</title>
    <link>https://www.47news.jp/14636911.html</link>
    <description></description>
    <dc:date>2026-07-17T00:00:00+09:00</dc:date>
  </item>
  <item rdf:about="https://www.47news.jp/14636322.html">
    <title>水面に映るオレンジと緑のライトアップ　群馬･グリーンドーム前橋、国スポ･全スポ開催で28日まで</title>
    <link>https://www.47news.jp/14636322.html</link>
    <description></description>
    <dc:date>2026-07-17T00:00:00+09:00</dc:date>
  </item>
  <item rdf:about="https://www.47news.jp/14636252.html">
    <title>「トチツーカ」生活支援は建前？　県「マイナ普及や地元消費も重点」　識者「本当に困っている人に届くか」</title>
    <link>https://www.47news.jp/14636252.html</link>
    <description></description>
    <dc:date>2026-07-17T00:00:00+09:00</dc:date>
  </item>
  <item rdf:about="https://www.47news.jp/14633802.html">
    <title>皇室典範、異論残し参院委可決　男系固執、17日成立</title>
    <link>https://www.47news.jp/14633802.html</link>
    <description></description>
    <dc:date>2026-07-17T00:00:00+09:00</dc:date>
  </item>
  <item rdf:about="https://www.47news.jp/14635356.html">
    <title>NHK受信契約、修正要求　全国知事会が提言を採択</title>
    <link>https://www.47news.jp/14635356.html</link>
    <description></description>
    <dc:date>2026-07-17T00:00:00+09:00</dc:date>
  </item>
  <item rdf:about="https://www.47news.jp/14632912.html">
    <title>今国会、会期延長へ　副首都法案17日成立困難</title>
    <link>https://www.47news.jp/14632912.html</link>
    <description></description>
    <dc:date>2026-07-17T00:00:00+09:00</dc:date>
  </item>
  <item rdf:about="https://www.47news.jp/14635076.html">
    <title>【速報】今国会、会期延長へ</title>
    <link>https://www.47news.jp/14635076.html</link>
    <description></description>
    <dc:date>2026-07-17T00:00:00+09:00</dc:date>
  </item>
  <item rdf:about="https://www.47news.jp/14632261.html">
    <title>日本国旗の損壊行為に刑罰　参院委可決、17日成立</title>
    <link>https://www.47news.jp/14632261.html</link>
    <description></description>
    <dc:date>2026-07-17T00:00:00+09:00</dc:date>
  </item>
  <item rdf:about="https://www.47news.jp/14634966.html">
    <title>投票所入場券はがき2万6097通の宛名を誤表記、長野市選管　投票に影響なし</title>
    <link>https://www.47news.jp/14634966.html</link>
    <description></description>
    <dc:date>2026-07-17T00:00:00+09:00</dc:date>
  </item>
  <item rdf:about="https://www.47news.jp/14634846.html">
    <title>鳥取市で全国知事会議始まる、行政サービスの共同化を国に提言へ　人口減少対策チームの設置決める　</title>
    <link>https://www.47news.jp/14634846.html</link>
    <description></description>
    <dc:date>2026-07-17T00:00:00+09:00</dc:date>
  </item>
  <item rdf:about="https://www.47news.jp/14631002.html">
    <title>知事会「地方税の偏在見直しを」　財政力の格差問題視、国に提言案</title>
    <link>https://www.47news.jp/14631002.html</link>
    <description></description>
    <dc:date>2026-07-17T00:00:00+09:00</dc:date>
  </item>
  <item rdf:about="https://www.47news.jp/14633802.html">
    <title>皇室典範、異論残し参院委可決　男系固執、17日成立</title>
    <link>https://www.47news.jp/14633802.html</link>
    <description></description>
    <dc:date>2026-07-17T00:00:00+09:00</dc:date>
  </item>
  <item rdf:about="https://www.47news.jp/14629683.html">
    <title>松本市民は姫路城入場が無料になる　11月、姫路市民には松本城を開放</title>
    <link>https://www.47news.jp/14629683.html</link>
    <description></description>
    <dc:date>2026-07-17T00:00:00+09:00</dc:date>
  </item>
  <item rdf:about="https://www.47news.jp/14632912.html">
    <title>今国会、会期延長へ　副首都法案17日成立困難</title>
    <link>https://www.47news.jp/14632912.html</link>
    <description></description>
    <dc:date>2026-07-17T00:00:00+09:00</dc:date>
  </item>
  <item rdf:about="https://www.47news.jp/14636322.html">
    <title>水面に映るオレンジと緑のライトアップ　群馬･グリーンドーム前橋、国スポ･全スポ開催で28日まで</title>
    <link>https://www.47news.jp/14636322.html</link>
    <description></description>
    <dc:date>2026-07-17T00:00:00+09:00</dc:date>
  </item>
  <item rdf:about="https://www.47news.jp/14636252.html">
    <title>「トチツーカ」生活支援は建前？　県「マイナ普及や地元消費も重点」　識者「本当に困っている人に届くか」</title>
    <link>https://www.47news.jp/14636252.html</link>
    <description></description>
    <dc:date>2026-07-17T00:00:00+09:00</dc:date>
  </item>
  <item rdf:about="https://www.47news.jp/special/kenes_03">
    <title>幅広い知識と技術で、顧客の省エネを支え続ける　最前線で奮闘するKenesの社員たち</title>
    <link>https://www.47news.jp/special/kenes_03</link>
    <description></description>
    <dc:date>2026-07-17T00:00:00+09:00</dc:date>
  </item>
  <item rdf:about="https://www.47news.jp/special/env_fukushima">
    <title>人の営みがよみがえり、願いは「当たり前」に戻ること　復興支える中間貯蔵施設のいま、2045年への約束</title>
    <link>https://www.47news.jp/special/env_fukushima</link>
    <description></description>
    <dc:date>2026-07-17T00:00:00+09:00</dc:date>
  </item>
  <item rdf:about="https://www.47news.jp/special/nayami_sodan">
    <title>もしも自分や身近な人が悩みを抱えたら？知っておきたい、「相談」の大切さ</title>
    <link>https://www.47news.jp/special/nayami_sodan</link>
    <description></description>
    <dc:date>2026-07-17T00:00:00+09:00</dc:date>
  </item>
  <item rdf:about="https://www.47news.jp/special/university-future">
    <title>大学特集〜大学教育の未来を探る〜</title>
    <link>https://www.47news.jp/special/university-future</link>
    <description></description>
    <dc:date>2026-07-17T00:00:00+09:00</dc:date>
  </item>
  <item rdf:about="https://www.47news.jp/special/e-fran_06">
    <title>創業5年で売り上げ50億円達成の背景に「自責」の精神　渡辺喜久男会長と塚本拓夢オーナーが「おたからや」の成功を語る</title>
    <link>https://www.47news.jp/special/e-fran_06</link>
    <description></description>
    <dc:date>2026-07-17T00:00:00+09:00</dc:date>
  </item>
  <item rdf:about="https://www.47news.jp/special/e-fran_05">
    <title>「おたからや」に学ぶ、FC経営成功の秘訣　大畑典道オーナーと渡辺喜久男会長が本音で語る</title>
    <link>https://www.47news.jp/special/e-fran_05</link>
    <description></description>
    <dc:date>2026-07-17T00:00:00+09:00</dc:date>
  </item>
  <item rdf:about="https://www.47news.jp/special/kenes_03">
    <title>幅広い知識と技術で、顧客の省エネを支え続ける　最前線で奮闘するKenesの社員たち</title>
    <link>https://www.47news.jp/special/kenes_03</link>
    <description></description>
    <dc:date>2026-07-17T00:00:00+09:00</dc:date>
  </item>
  <item rdf:about="https://www.47news.jp/special/env_fukushima">
    <title>人の営みがよみがえり、願いは「当たり前」に戻ること　復興支える中間貯蔵施設のいま、2045年への約束</title>
    <link>https://www.47news.jp/special/env_fukushima</link>
    <description></description>
    <dc:date>2026-07-17T00:00:00+09:00</dc:date>
  </item>
</rdf:RDF>
